rerankers/__init__.py
rerankers/documents.py
rerankers/reranker.py
rerankers/results.py
rerankers/utils.py
rerankers/integrations/__init__.py
rerankers/integrations/langchain.py
rerankers/models/__init__.py
rerankers/models/api_rankers.py
rerankers/models/colbert_ranker.py
rerankers/models/flashrank_ranker.py
rerankers/models/llm_layerwise_ranker.py
rerankers/models/llm_relevance_filter.py
rerankers/models/monovlm_ranker.py
rerankers/models/mxbai_v2.py
rerankers/models/ranker.py
rerankers/models/rankgpt_rankers.py
rerankers/models/rankllm_ranker.py
rerankers/models/t5ranker.py
rerankers/models/transformer_ranker.py
rerankers/models/upr.py
rerankers-0.9.1.post1.dist-info/licenses/LICENSE
rerankers-0.9.1.post1.dist-info/METADATA
rerankers-0.9.1.post1.dist-info/WHEEL
rerankers-0.9.1.post1.dist-info/top_level.txt
rerankers-0.9.1.post1.dist-info/RECORD
