Metadata-Version: 2.4
Name: rerankers
Version: 0.9.1.post1
Summary: A unified API for various document re-ranking models.
Author-email: Ben Clavié <bc@answer.ai>
Maintainer-email: Ben Clavié <bc@answer.ai>
License:  Apache License
Project-URL: Homepage, https://github.com/answerdotai/rerankers
Keywords: reranking,retrieval,rag,nlp
Classifier: Programming Language :: Python :: 3
Classifier: Programming Language :: Python :: 3.8
Classifier: Programming Language :: Python :: 3.9
Classifier: Programming Language :: Python :: 3.10
Classifier: Programming Language :: Python :: 3.11
Classifier: Programming Language :: Python :: 3.12
Classifier: Programming Language :: Python :: 3 :: Only
Requires-Python: >=3.8
License-File: LICENSE
Provides-Extra: all
Requires-Dist: transformers>=4.45.0; extra == "all"
Requires-Dist: torch; extra == "all"
Requires-Dist: litellm; extra == "all"
Requires-Dist: requests; extra == "all"
Requires-Dist: sentencepiece; extra == "all"
Requires-Dist: protobuf; extra == "all"
Requires-Dist: flashrank; extra == "all"
Requires-Dist: flash-attn; extra == "all"
Requires-Dist: pillow; extra == "all"
Requires-Dist: accelerate>=0.26.0; extra == "all"
Requires-Dist: peft>=0.13.0; extra == "all"
Requires-Dist: nmslib-metabrainz; python_version >= "3.10" and extra == "all"
Requires-Dist: rank-llm; python_version >= "3.10" and extra == "all"
Provides-Extra: transformers
Requires-Dist: transformers>=4.45.0; extra == "transformers"
Requires-Dist: torch; extra == "transformers"
Requires-Dist: sentencepiece; extra == "transformers"
Requires-Dist: protobuf; extra == "transformers"
Provides-Extra: api
Requires-Dist: requests; extra == "api"
Provides-Extra: gpt
Requires-Dist: litellm; extra == "gpt"
Provides-Extra: flashrank
Requires-Dist: flashrank; extra == "flashrank"
Provides-Extra: llmlayerwise
Requires-Dist: transformers>=4.45.0; extra == "llmlayerwise"
Requires-Dist: torch; extra == "llmlayerwise"
Requires-Dist: sentencepiece; extra == "llmlayerwise"
Requires-Dist: protobuf; extra == "llmlayerwise"
Requires-Dist: flash-attn; extra == "llmlayerwise"
Provides-Extra: monovlm
Requires-Dist: transformers>=4.45.0; extra == "monovlm"
Requires-Dist: torch; extra == "monovlm"
Requires-Dist: sentencepiece; extra == "monovlm"
Requires-Dist: protobuf; extra == "monovlm"
Requires-Dist: flash-attn; extra == "monovlm"
Requires-Dist: pillow; extra == "monovlm"
Requires-Dist: accelerate>=0.26.0; extra == "monovlm"
Requires-Dist: peft>=0.13.0; extra == "monovlm"
Provides-Extra: rankllm
Requires-Dist: nmslib-metabrainz; python_version >= "3.10" and extra == "rankllm"
Requires-Dist: rank-llm; python_version >= "3.10" and extra == "rankllm"
Provides-Extra: dev
Requires-Dist: ruff; extra == "dev"
Requires-Dist: isort; extra == "dev"
Requires-Dist: pytest; extra == "dev"
Requires-Dist: ipyprogress; extra == "dev"
Requires-Dist: ipython; extra == "dev"
Requires-Dist: ranx; extra == "dev"
Requires-Dist: ir_datasets; extra == "dev"
Requires-Dist: srsly; extra == "dev"
Dynamic: license-file
